azure_sql_vector_search/__init__.py
azure_sql_vector_search/classic_vector_search.py
azure_sql_vector_search/models.py
azure_sql_vector_search/native_vector_search.py
azure_sql_vector_search/vector_search_base.py
azure_sql_vector_search-0.8.3.dist-info/LICENSE
azure_sql_vector_search-0.8.3.dist-info/METADATA
azure_sql_vector_search-0.8.3.dist-info/WHEEL
azure_sql_vector_search-0.8.3.dist-info/top_level.txt
azure_sql_vector_search-0.8.3.dist-info/RECORD
