Metadata-Version: 2.1
Name: azure-sql-vector-search
Version: 0.8.3
Summary: Azure SQL Vector Search Clients
Home-page: https://github.com/projectAcetylcholine/sql_vector_search
Author: Microsoft Corporation
License: MIT License
Keywords: azure sql vector search langchain
License-File: LICENSE
Requires-Dist: pyodbc >=5.1.0
Requires-Dist: sqlalchemy >=2.0.30
Requires-Dist: numpy >=1.26.4
